{
  "id": 1007,
  "name": "Job WIP Warning",
  "slug": "1007_job_wip_warning",
  "objectNamespace": "Base Application",
  "fields": [
    {
      "no": 1,
      "name": "Entry No.",
      "tooltip": ""
    },
    {
      "no": 2,
      "name": "Job No.",
      "tooltip": "Specifies the number of the related project."
    },
    {
      "no": 3,
      "name": "Job Task No.",
      "tooltip": "Specifies the number of the related project task."
    },
    {
      "no": 4,
      "name": "Job WIP Total Entry No.",
      "tooltip": "Specifies the entry number from the associated project WIP total."
    },
    {
      "no": 5,
      "name": "Warning Message",
      "tooltip": "Specifies a warning message that is related to a project WIP calculation."
    }
  ]
}