{
  "id": 5901,
  "name": "Service Item Line",
  "slug": "5901_service_item_line",
  "objectNamespace": "Base Application",
  "fields": [
    {
      "no": 1,
      "name": "Document No.",
      "tooltip": "Specifies the number of the service order linked to this service item line."
    },
    {
      "no": 2,
      "name": "Line No.",
      "tooltip": "Specifies the number of the line."
    },
    {
      "no": 3,
      "name": "Service Item No.",
      "tooltip": "Specifies the service item number registered in the Service Item table."
    },
    {
      "no": 4,
      "name": "Service Item Group Code",
      "tooltip": "Specifies the code of the service item group for this item."
    },
    {
      "no": 5,
      "name": "Item No.",
      "tooltip": "Specifies the item number linked to this service item."
    },
    {
      "no": 6,
      "name": "Serial No.",
      "tooltip": "Specifies the serial number of this item."
    },
    {
      "no": 7,
      "name": "Description",
      "tooltip": "Specifies a description of this service item."
    },
    {
      "no": 8,
      "name": "Description 2",
      "tooltip": "Specifies information in addition to the description."
    },
    {
      "no": 9,
      "name": "Repair Status Code",
      "tooltip": "Specifies the repair status of this service item."
    },
    {
      "no": 10,
      "name": "Priority",
      "tooltip": "Specifies the service priority for this item."
    },
    {
      "no": 11,
      "name": "Response Time (Hours)",
      "tooltip": "Specifies the estimated hours from order creation, to the time when the repair status of the item line changes from Initial, to In Process."
    },
    {
      "no": 12,
      "name": "Response Date",
      "tooltip": "Specifies the estimated date when service should start on this service item line."
    },
    {
      "no": 13,
      "name": "Response Time",
      "tooltip": "Specifies the estimated time when service should start on this service item."
    },
    {
      "no": 14,
      "name": "Starting Date",
      "tooltip": "Specifies the date when service on this item began and when the repair status changed to In process."
    },
    {
      "no": 15,
      "name": "Starting Time",
      "tooltip": "Specifies the time when service on this item began and when the repair status changed to In process."
    },
    {
      "no": 16,
      "name": "Finishing Date",
      "tooltip": "Specifies the finishing date of the service and when the repair status of this item changes to Finished."
    },
    {
      "no": 17,
      "name": "Finishing Time",
      "tooltip": "Specifies the finishing time of the service and when the repair status of this item changes to Finished."
    },
    {
      "no": 18,
      "name": "Service Shelf No.",
      "tooltip": "Specifies the number of the service shelf this item is stored on."
    },
    {
      "no": 19,
      "name": "Warranty Starting Date (Parts)",
      "tooltip": "Specifies the starting date of the spare parts warranty for this item."
    },
    {
      "no": 20,
      "name": "Warranty Ending Date (Parts)",
      "tooltip": "Specifies the ending date of the spare parts warranty for this item."
    },
    {
      "no": 21,
      "name": "Warranty",
      "tooltip": "Specifies that warranty on either parts or labor exists for this item."
    },
    {
      "no": 22,
      "name": "Warranty % (Parts)",
      "tooltip": "Specifies the percentage of spare parts costs covered by the warranty for this item."
    },
    {
      "no": 23,
      "name": "Warranty % (Labor)",
      "tooltip": "Specifies the percentage of labor costs covered by the warranty for this item."
    },
    {
      "no": 24,
      "name": "Warranty Starting Date (Labor)",
      "tooltip": "Specifies the starting date of the labor warranty for this item."
    },
    {
      "no": 25,
      "name": "Warranty Ending Date (Labor)",
      "tooltip": "Specifies the ending date of the labor warranty for this item."
    },
    {
      "no": 26,
      "name": "Contract No.",
      "tooltip": "Specifies the number of the service contract associated with the item or service on the line."
    },
    {
      "no": 27,
      "name": "Location of Service Item",
      "tooltip": "Specifies the code of the location of this item."
    },
    {
      "no": 28,
      "name": "Loaner No.",
      "tooltip": "Specifies the number of the loaner that has been lent to the customer in the service order to replace this item."
    },
    {
      "no": 29,
      "name": "Vendor No.",
      "tooltip": "Specifies the number of the vendor of this item."
    },
    {
      "no": 30,
      "name": "Vendor Item No.",
      "tooltip": "Specifies the number that the vendor uses for this item."
    },
    {
      "no": 31,
      "name": "Fault Reason Code",
      "tooltip": "Specifies the fault reason code for the item."
    },
    {
      "no": 32,
      "name": "Service Price Group Code",
      "tooltip": "Specifies the code of the service price group associated with the item."
    },
    {
      "no": 33,
      "name": "Fault Area Code",
      "tooltip": "Specifies the fault area code for this item."
    },
    {
      "no": 34,
      "name": "Symptom Code",
      "tooltip": "Specifies the symptom code for this item."
    },
    {
      "no": 35,
      "name": "Fault Code",
      "tooltip": "Specifies the fault code for this item."
    },
    {
      "no": 36,
      "name": "Resolution Code",
      "tooltip": "Specifies the resolution code for this item."
    },
    {
      "no": 37,
      "name": "Fault Comment",
      "tooltip": "Specifies that there is a fault comment for this service item. For example, this can be information about what is wrong with the item or what service needs to be done."
    },
    {
      "no": 38,
      "name": "Resolution Comment",
      "tooltip": "Specifies that there is a resolution comment for this service item. For example, this can be information about the method that the technician uses to resolve the problem with the item."
    },
    {
      "no": 40,
      "name": "Variant Code",
      "tooltip": "Specifies the variant of the item on the line."
    },
    {
      "no": 41,
      "name": "Service Item Loaner Comment",
      "tooltip": "Specifies that there is a loaner comment for this service item."
    },
    {
      "no": 42,
      "name": "Actual Response Time (Hours)",
      "tooltip": "Contains the actual number of hours from the creation of the service order to the time when the repair status of this service item changes from Initial to In Process.\nThe program automatically calculates the contents of this field using the order date and order time values in the Service Header table and the Starting Date and Starting Time fields in the Service Item Line table."
    },
    {
      "no": 43,
      "name": "Document Type",
      "tooltip": "Specifies whether the service document is a service order or service quote."
    },
    {
      "no": 44,
      "name": "Serv. Price Adjmt. Gr. Code",
      "tooltip": "Contains the service price adjustment group code that applies to the current service item line. The program automatically copies the code from the Service Price Adjustment Group table."
    },
    {
      "no": 45,
      "name": "Adjustment Type",
      "tooltip": "Specifies the adjustment type for the line."
    },
    {
      "no": 46,
      "name": "Base Amount to Adjust",
      "tooltip": "Specifies the amount that the service line, linked to this service item line, will be adjusted to."
    },
    {
      "no": 60,
      "name": "No. of Active/Finished Allocs",
      "tooltip": "Contains the number of active or finished resource allocations for this service item.\nThe program automatically calculates and updates the contents of this field using the entries with an Active or Finished status in the Service Order Allocation table."
    },
    {
      "no": 61,
      "name": "No. of Allocations",
      "tooltip": "Specifies the number of resource allocations with the allocation status specified in the Allocation Status Filter field."
    },
    {
      "no": 62,
      "name": "No. of Previous Services",
      "tooltip": "Specifies the number of services performed on service items with the same item and serial number as this service item."
    },
    {
      "no": 63,
      "name": "Contract Line No.",
      "tooltip": "Contains the number of the contract line that you created.\nIf the service item line was created by the Create Contract Service Orders batch job, this is the reference line from the Service Contract Line table.\nA service contract can have several contract lines. Assigning a number to each line makes it possible to differentiate between them."
    },
    {
      "no": 64,
      "name": "Ship-to Code",
      "tooltip": "Specifies the ship-to code of the service item associated with the service contract or service order."
    },
    {
      "no": 65,
      "name": "Customer No.",
      "tooltip": "Specifies the customer number associated with the service contract."
    },
    {
      "no": 91,
      "name": "Date Filter",
      "tooltip": "Specifies the date interval that values are filtered by.\nIf this field contains starting and ending dates for a date interval, then other field values only show information for that interval.\nYou can enter a date interval according to the following rules.\n\n\nMeaning\n\n\nSample expression\n\n\nEntries that are included\n\n\nEqual to\n\n12 15 12\n\nOnly entries that are posted on December 15, 2012.\n\n\nInterval\n\n12 15 12..01 15 13\n..12 15 12\n\nEntries that are posted on dates between and including December 15, 2012, and January 15, 2013.\nEntries that are posted on January 15, 2012, or earlier.\n\n\nEither/or\n\n12 15 12|12 16 12\n\nEntries that are posted on either December 15, 2012, or December 16, 2012. If there are entries that are posted on both days, then all entries are displayed.\n\n\nYou can also combine the various format types.\n\n\nSample expression\n\n\nEntries that are included\n\n\n12 15 12|12 01 12..12 10 12\n\nEntries that are posted either on December 15, 2012, or on dates between and including December 1, 2012, and December 10, 2012.\n\n\n..12 14 12|12 30 12..\n\nEntries that are posted on December 14, 2012, or earlier, or entries that are posted on December 30, 2012, or later, which includes all entries except those that are posted on dates between and including December 15, 2012, and December 29, 2012."
    },
    {
      "no": 92,
      "name": "Resource Filter",
      "tooltip": "Contains a resource filter.\nIf this field contains a particular resource number, fields such as the No. of Allocations field will only display information on service order allocations with that resource. The Service Tasks window will also show the service tasks corresponding to the service item lines that the specified resource is allocated to (provided that you use allocation in your company)."
    },
    {
      "no": 93,
      "name": "Allocation Date Filter",
      "tooltip": "Contains a date filter.\nIf this field contains the starting and ending dates for a time period, fields such as the No. of Active/Finished Allocs display information for that time period only."
    },
    {
      "no": 94,
      "name": "Repair Status Code Filter",
      "tooltip": "Contains a repair status code filter.\nIf this field contains a repair status code, the Service Tasks window shows service item lines with that particular repair status only."
    },
    {
      "no": 96,
      "name": "Allocation Status Filter",
      "tooltip": "Contains an allocation status filter. There are five options: Nonactive, Active, Finished, Canceled and Reallocation Needed.\nFor example, if this field contains the option Reallocation Needed, fields such as the No. of Allocations field only display information on service order allocations with that particular status."
    },
    {
      "no": 97,
      "name": "Responsibility Center",
      "tooltip": "Contains the code of the responsibility center that is associated either with the customer in the service order, or with your company.\nThe program copies the code automatically from the Responsibility Center field in the Service Header table."
    },
    {
      "no": 98,
      "name": "Service Order Filter",
      "tooltip": "Specifies a filter that filters service order lines by service order number."
    },
    {
      "no": 99,
      "name": "Resource Group Filter",
      "tooltip": "Contains a resource group filter.\nIf this field contains a particular resource group number, fields such as the No. of Allocations field will only display information on service order allocations with that resource group. The Service Tasks window will also show the service tasks corresponding to the service item lines the specified resource group is allocated to (provided that you use allocation in your company)."
    },
    {
      "no": 100,
      "name": "Shortcut Dimension 1 Code",
      "tooltip": "Contains the value of Shortcut Dimension 1 defined in the Shortcut Dimension 1 Code field in the General Ledger Setup window.\n\nYou cannot change the contents of this field."
    },
    {
      "no": 101,
      "name": "Shortcut Dimension 2 Code",
      "tooltip": "Contains the value of Shortcut Dimension 2 defined in the Shortcut Dimension 2 Code field in the General Ledger Setup window.\n\nYou cannot change the contents of this field."
    },
    {
      "no": 130,
      "name": "Release Status",
      "tooltip": "Specifies the status of a service item line. The options are the following:\nOpen\n\nReleased to Ship"
    },
    {
      "no": 480,
      "name": "Dimension Set ID",
      "tooltip": "Specifies a reference to a combination of dimension values. The actual values are stored in the Dimension Set Entry table.\n\n\nAdditional Information\n\n\nThe dimension set ID is not edited directly by users. The value of the field is calculated with the dimension values that users select in the Edit Dimension Set Entries window.\n\n\nThe value 0 represents an empty dimension set."
    }
  ]
}